{"cod": "200", "message": 0, "cnt": 40, "list": [{"dt": 1572631200, "main": {"temp": 278.21, "temp_min": 278.21, "temp_max": 280.75, "pressure": 1025, "sea_level": 1025, "grnd_level": 1014, "humidity": 42, "temp_kf": -2.55}, "weather": [{"id": 800, "main": "Clear", "description": "clear sky", "icon": "01n"}], "clouds": {"all": 0}, "wind": {"speed": 1.97, "deg": 99}, "sys": {"pod": "n"}, "dt_txt": "2019-11-01 18:00:00"}, {"dt": 1572642000, "main": {"temp": 277.8, "temp_min": 277.8, "temp_max": 279.71, "pressure": 1025, "sea_level": 1025, "grnd_level": 1013, "humidity": 44, "temp_kf": -1.91}, "weather": [{"id": 800, "main": "Clear", "description": "clear sky", "icon": "01n"}], "clouds": {"all": 0}, "wind": {"speed": 2.39, "deg": 88}, "sys": {"pod": "n"}, "dt_txt": "2019-11-01 21:00:00"}, {"dt": 1572652800, "main": {"temp": 277.42, "temp_min": 277.42, "temp_max": 278.69, "pressure": 1024, "sea_level": 1024, "grnd_level": 1013, "humidity": 63, "temp_kf": -1.28}, "weather": [{"id": 800, "main": "Clear", "description": "clear sky", "icon": "01n"}], "clouds": {"all": 0}, "wind": {"speed": 2.24, "deg": 66}, "sys": {"pod": "n"}, "dt_txt": "2019-11-02 00:00:00"}, {"dt": 1572663600, "main": {"temp": 278.22, "temp_min": 278.22, "temp_max": 278.86, "pressure": 1022, "sea_level": 1022, "grnd_level": 1011, "humidity": 79, "temp_kf": -0.64}, "weather": [{"id": 802, "main": "Clouds", "description": "scattered clouds", "icon": "03n"}], "clouds": {"all": 32}, "wind": {"speed": 3.01, "deg": 66}, "sys": {"pod": "n"}, "dt_txt": "2019-11-02 03:00:00"}, {"dt": 1572674400, "main": {"temp": 280.2, "temp_min": 280.2, "temp_max": 280.2, "pressure": 1022, "sea_level": 1022, "grnd_level": 1010, "humidity": 80, "temp_kf": 0}, "weather": [{"id": 803, "main": "Clouds", "description": "broken clouds", "icon": "04d"}], "clouds": {"all": 63}, "wind": {"speed": 3.13, "deg": 113}, "sys": {"pod": "d"}, "dt_txt": "2019-11-02 06:00:00"}, {"dt": 1572685200, "main": {"temp": 283.72, "temp_min": 283.72, "temp_max": 283.72, "pressure": 1020, "sea_level": 1020, "grnd_level": 1009, "humidity": 65, "temp_kf": 0}, "weather": [{"id": 804, "main": "Clouds", "description": "overcast clouds", "icon": "04d"}], "clouds": {"all": 98}, "wind": {"speed": 3.45, "deg": 159}, "sys": {"pod": "d"}, "dt_txt": "2019-11-02 09:00:00"}, {"dt": 1572696000, "main": {"temp": 286.26, "temp_min": 286.26, "temp_max": 286.26, "pressure": 1019, "sea_level": 1019, "grnd_level": 1007, "humidity": 54, "temp_kf": 0}, "weather": [{"id": 804, "main": "Clouds", "description": "overcast clouds", "icon": "04d"}], "clouds": {"all": 99}, "wind": {"speed": 2.34, "deg": 166}, "sys": {"pod": "d"}, "dt_txt": "2019-11-02 12:00:00"}, {"dt": 1572706800, "main": {"temp": 285.39, "temp_min": 285.39, "temp_max": 285.39, "pressure": 1017, "sea_level": 1017, "grnd_level": 1005, "humidity": 58, "temp_kf": 0}, "weather": [{"id": 803, "main": "Clouds", "description": "broken clouds", "icon": "04d"}], "clouds": {"all": 79}, "wind": {"speed": 2.08, "deg": 131}, "sys": {"pod": "d"}, "dt_txt": "2019-11-02 15:00:00"}, {"dt": 1572717600, "main": {"temp": 284.03, "temp_min": 284.03, "temp_max": 284.03, "pressure": 1018, "sea_level": 1018, "grnd_level": 1006, "humidity": 64, "temp_kf": 0}, "weather": [{"id": 803, "main": "Clouds", "description": "broken clouds", "icon": "04n"}], "clouds": {"all": 83}, "wind": {"speed": 2.01, "deg": 143}, "sys": {"pod": "n"}, "dt_txt": "2019-11-02 18:00:00"}, {"dt": 1572728400, "main": {"temp": 282.78, "temp_min": 282.78, "temp_max": 282.78, "pressure": 1017, "sea_level": 1017, "grnd_level": 1005, "humidity": 68, "temp_kf": 0}, "weather": [{"id": 803, "main": "Clouds", "description": "broken clouds", "icon": "04n"}], "clouds": {"all": 51}, "wind": {"speed": 1.22, "deg": 135}, "sys": {"pod": "n"}, "dt_txt": "2019-11-02 21:00:00"}, {"dt": 1572739200, "main": {"temp": 282.06, "temp_min": 282.06, "temp_max": 282.06, "pressure": 1016, "sea_level": 1016, "grnd_level": 1004, "humidity": 72, "temp_kf": 0}, "weather": [{"id": 802, "main": "Clouds", "description": "scattered clouds", "icon": "03n"}], "clouds": {"all": 42}, "wind": {"speed": 1.12, "deg": 134}, "sys": {"pod": "n"}, "dt_txt": "2019-11-03 00:00:00"}, {"dt": 1572750000, "main": {"temp": 281.79, "temp_min": 281.79, "temp_max": 281.79, "pressure": 1014, "sea_level": 1014, "grnd_level": 1003, "humidity": 73, "temp_kf": 0}, "weather": [{"id": 803, "main": "Clouds", "description": "broken clouds", "icon": "04n"}], "clouds": {"all": 55}, "wind": {"speed": 0.41, "deg": 143}, "sys": {"pod": "n"}, "dt_txt": "2019-11-03 03:00:00"}, {"dt": 1572760800, "main": {"temp": 282.39, "temp_min": 282.39, "temp_max": 282.39, "pressure": 1014, "sea_level": 1014, "grnd_level": 1003, "humidity": 70, "temp_kf": 0}, "weather": [{"id": 803, "main": "Clouds", "description": "broken clouds", "icon": "04d"}], "clouds": {"all": 66}, "wind": {"speed": 0.79, "deg": 109}, "sys": {"pod": "d"}, "dt_txt": "2019-11-03 06:00:00"}, {"dt": 1572771600, "main": {"temp": 285.8, "temp_min": 285.8, "temp_max": 285.8, "pressure": 1013, "sea_level": 1013, "grnd_level": 1002, "humidity": 55, "temp_kf": 0}, "weather": [{"id": 804, "main": "Clouds", "description": "overcast clouds", "icon": "04d"}], "clouds": {"all": 95}, "wind": {"speed": 0.97, "deg": 190}, "sys": {"pod": "d"}, "dt_txt": "2019-11-03 09:00:00"}, {"dt": 1572782400, "main": {"temp": 287.9, "temp_min": 287.9, "temp_max": 287.9, "pressure": 1011, "sea_level": 1011, "grnd_level": 1001, "humidity": 47, "temp_kf": 0}, "weather": [{"id": 804, "main": "Clouds", "description": "overcast clouds", "icon": "04d"}], "clouds": {"all": 98}, "wind": {"speed": 1.36, "deg": 168}, "sys": {"pod": "d"}, "dt_txt": "2019-11-03 12:00:00"}, {"dt": 1572793200, "main": {"temp": 287.05, "temp_min": 287.05, "temp_max": 287.05, "pressure": 1010, "sea_level": 1010, "grnd_level": 999, "humidity": 51, "temp_kf": 0}, "weather": [{"id": 804, "main": "Clouds", "description": "overcast clouds", "icon": "04d"}], "clouds": {"all": 100}, "wind": {"speed": 0.95, "deg": 121}, "sys": {"pod": "d"}, "dt_txt": "2019-11-03 15:00:00"}, {"dt": 1572804000, "main": {"temp": 286.35, "temp_min": 286.35, "temp_max": 286.35, "pressure": 1010, "sea_level": 1010, "grnd_level": 999, "humidity": 53, "temp_kf": 0}, "weather": [{"id": 804, "main": "Clouds", "description": "overcast clouds", "icon": "04n"}], "clouds": {"all": 100}, "wind": {"speed": 1.62, "deg": 54}, "sys": {"pod": "n"}, "dt_txt": "2019-11-03 18:00:00"}, {"dt": 1572814800, "main": {"temp": 285.46, "temp_min": 285.46, "temp_max": 285.46, "pressure": 1010, "sea_level": 1010, "grnd_level": 999, "humidity": 56, "temp_kf": 0}, "weather": [{"id": 804, "main": "Clouds", "description": "overcast clouds", "icon": "04n"}], "clouds": {"all": 100}, "wind": {"speed": 1.3, "deg": 3}, "sys": {"pod": "n"}, "dt_txt": "2019-11-03 21:00:00"}, {"dt": 1572825600, "main": {"temp": 285.12, "temp_min": 285.12, "temp_max": 285.12, "pressure": 1009, "sea_level": 1009, "grnd_level": 998, "humidity": 58, "temp_kf": 0}, "weather": [{"id": 804, "main": "Clouds", "description": "overcast clouds", "icon": "04n"}], "clouds": {"all": 100}, "wind": {"speed": 0.39, "deg": 219}, "sys": {"pod": "n"}, "dt_txt": "2019-11-04 00:00:00"}, {"dt": 1572836400, "main": {"temp": 284.76, "temp_min": 284.76, "temp_max": 284.76, "pressure": 1008, "sea_level": 1008, "grnd_level": 997, "humidity": 62, "temp_kf": 0}, "weather": [{"id": 804, "main": "Clouds", "description": "overcast clouds", "icon": "04n"}], "clouds": {"all": 100}, "wind": {"speed": 1.2, "deg": 148}, "sys": {"pod": "n"}, "dt_txt": "2019-11-04 03:00:00"}, {"dt": 1572847200, "main": {"temp": 284.87, "temp_min": 284.87, "temp_max": 284.87, "pressure": 1007, "sea_level": 1007, "grnd_level": 997, "humidity": 67, "temp_kf": 0}, "weather": [{"id": 803, "main": "Clouds", "description": "broken clouds", "icon": "04d"}], "clouds": {"all": 66}, "wind": {"speed": 1.54, "deg": 98}, "sys": {"pod": "d"}, "dt_txt": "2019-11-04 06:00:00"}, {"dt": 1572858000, "main": {"temp": 289.06, "temp_min": 289.06, "temp_max": 289.06, "pressure": 1006, "sea_level": 1006, "grnd_level": 995, "humidity": 58, "temp_kf": 0}, "weather": [{"id": 802, "main": "Clouds", "description": "scattered clouds", "icon": "03d"}], "clouds": {"all": 33}, "wind": {"speed": 1.79, "deg": 124}, "sys": {"pod": "d"}, "dt_txt": "2019-11-04 09:00:00"}, {"dt": 1572868800, "main": {"temp": 292.74, "temp_min": 292.74, "temp_max": 292.74, "pressure": 1004, "sea_level": 1004, "grnd_level": 993, "humidity": 51, "temp_kf": 0}, "weather": [{"id": 803, "main": "Clouds", "description": "broken clouds", "icon": "04d"}], "clouds": {"all": 67}, "wind": {"speed": 0.89, "deg": 52}, "sys": {"pod": "d"}, "dt_txt": "2019-11-04 12:00:00"}, {"dt": 1572879600, "main": {"temp": 290.3, "temp_min": 290.3, "temp_max": 290.3, "pressure": 1004, "sea_level": 1004, "grnd_level": 992, "humidity": 60, "temp_kf": 0}, "weather": [{"id": 804, "main": "Clouds", "description": "overcast clouds", "icon": "04d"}], "clouds": {"all": 97}, "wind": {"speed": 2.56, "deg": 342}, "sys": {"pod": "d"}, "dt_txt": "2019-11-04 15:00:00"}, {"dt": 1572890400, "main": {"temp": 289.38, "temp_min": 289.38, "temp_max": 289.38, "pressure": 1005, "sea_level": 1005, "grnd_level": 994, "humidity": 63, "temp_kf": 0}, "weather": [{"id": 804, "main": "Clouds", "description": "overcast clouds", "icon": "04n"}], "clouds": {"all": 97}, "wind": {"speed": 2.38, "deg": 140}, "sys": {"pod": "n"}, "dt_txt": "2019-11-04 18:00:00"}, {"dt": 1572901200, "main": {"temp": 288.69, "temp_min": 288.69, "temp_max": 288.69, "pressure": 1005, "sea_level": 1005, "grnd_level": 994, "humidity": 86, "temp_kf": 0}, "weather": [{"id": 500, "main": "Rain", "description": "light rain", "icon": "10n"}], "clouds": {"all": 100}, "wind": {"speed": 2.52, "deg": 251}, "rain": {"3h": 1.81}, "sys": {"pod": "n"}, "dt_txt": "2019-11-04 21:00:00"}, {"dt": 1572912000, "main": {"temp": 287.9, "temp_min": 287.9, "temp_max": 287.9, "pressure": 1007, "sea_level": 1007, "grnd_level": 995, "humidity": 72, "temp_kf": 0}, "weather": [{"id": 500, "main": "Rain", "description": "light rain", "icon": "10n"}], "clouds": {"all": 100}, "wind": {"speed": 3.92, "deg": 253}, "rain": {"3h": 0.44}, "sys": {"pod": "n"}, "dt_txt": "2019-11-05 00:00:00"}, {"dt": 1572922800, "main": {"temp": 286.23, "temp_min": 286.23, "temp_max": 286.23, "pressure": 1008, "sea_level": 1008, "grnd_level": 997, "humidity": 76, "temp_kf": 0}, "weather": [{"id": 800, "main": "Clear", "description": "clear sky", "icon": "01n"}], "clouds": {"all": 0}, "wind": {"speed": 4.49, "deg": 254}, "sys": {"pod": "n"}, "dt_txt": "2019-11-05 03:00:00"}, {"dt": 1572933600, "main": {"temp": 285.6, "temp_min": 285.6, "temp_max": 285.6, "pressure": 1010, "sea_level": 1010, "grnd_level": 999, "humidity": 78, "temp_kf": 0}, "weather": [{"id": 800, "main": "Clear", "description": "clear sky", "icon": "01d"}], "clouds": {"all": 0}, "wind": {"speed": 4.38, "deg": 251}, "sys": {"pod": "d"}, "dt_txt": "2019-11-05 06:00:00"}, {"dt": 1572944400, "main": {"temp": 289.68, "temp_min": 289.68, "temp_max": 289.68, "pressure": 1011, "sea_level": 1011, "grnd_level": 1000, "humidity": 58, "temp_kf": 0}, "weather": [{"id": 800, "main": "Clear", "description": "clear sky", "icon": "01d"}], "clouds": {"all": 0}, "wind": {"speed": 4.06, "deg": 258}, "sys": {"pod": "d"}, "dt_txt": "2019-11-05 09:00:00"}, {"dt": 1572955200, "main": {"temp": 292.52, "temp_min": 292.52, "temp_max": 292.52, "pressure": 1010, "sea_level": 1010, "grnd_level": 999, "humidity": 47, "temp_kf": 0}, "weather": [{"id": 800, "main": "Clear", "description": "clear sky", "icon": "01d"}], "clouds": {"all": 0}, "wind": {"speed": 3.81, "deg": 254}, "sys": {"pod": "d"}, "dt_txt": "2019-11-05 12:00:00"}, {"dt": 1572966000, "main": {"temp": 290.79, "temp_min": 290.79, "temp_max": 290.79, "pressure": 1009, "sea_level": 1009, "grnd_level": 998, "humidity": 54, "temp_kf": 0}, "weather": [{"id": 800, "main": "Clear", "description": "clear sky", "icon": "01d"}], "clouds": {"all": 0}, "wind": {"speed": 1.4, "deg": 241}, "sys": {"pod": "d"}, "dt_txt": "2019-11-05 15:00:00"}, {"dt": 1572976800, "main": {"temp": 289.49, "temp_min": 289.49, "temp_max": 289.49, "pressure": 1010, "sea_level": 1010, "grnd_level": 999, "humidity": 57, "temp_kf": 0}, "weather": [{"id": 800, "main": "Clear", "description": "clear sky", "icon": "01n"}], "clouds": {"all": 8}, "wind": {"speed": 0.84, "deg": 128}, "sys": {"pod": "n"}, "dt_txt": "2019-11-05 18:00:00"}, {"dt": 1572987600, "main": {"temp": 288.16, "temp_min": 288.16, "temp_max": 288.16, "pressure": 1010, "sea_level": 1010, "grnd_level": 999, "humidity": 60, "temp_kf": 0}, "weather": [{"id": 800, "main": "Clear", "description": "clear sky", "icon": "01n"}], "clouds": {"all": 1}, "wind": {"speed": 1.08, "deg": 84}, "sys": {"pod": "n"}, "dt_txt": "2019-11-05 21:00:00"}, {"dt": 1572998400, "main": {"temp": 287.01, "temp_min": 287.01, "temp_max": 287.01, "pressure": 1009, "sea_level": 1009, "grnd_level": 997, "humidity": 69, "temp_kf": 0}, "weather": [{"id": 800, "main": "Clear", "description": "clear sky", "icon": "01n"}], "clouds": {"all": 1}, "wind": {"speed": 0.98, "deg": 54}, "sys": {"pod": "n"}, "dt_txt": "2019-11-06 00:00:00"}, {"dt": 1573009200, "main": {"temp": 286.17, "temp_min": 286.17, "temp_max": 286.17, "pressure": 1008, "sea_level": 1008, "grnd_level": 996, "humidity": 74, "temp_kf": 0}, "weather": [{"id": 800, "main": "Clear", "description": "clear sky", "icon": "01n"}], "clouds": {"all": 0}, "wind": {"speed": 0.26, "deg": 352}, "sys": {"pod": "n"}, "dt_txt": "2019-11-06 03:00:00"}, {"dt": 1573020000, "main": {"temp": 286.39, "temp_min": 286.39, "temp_max": 286.39, "pressure": 1007, "sea_level": 1007, "grnd_level": 996, "humidity": 74, "temp_kf": 0}, "weather": [{"id": 800, "main": "Clear", "description": "clear sky", "icon": "01d"}], "clouds": {"all": 0}, "wind": {"speed": 1.08, "deg": 217}, "sys": {"pod": "d"}, "dt_txt": "2019-11-06 06:00:00"}, {"dt": 1573030800, "main": {"temp": 290.85, "temp_min": 290.85, "temp_max": 290.85, "pressure": 1007, "sea_level": 1007, "grnd_level": 996, "humidity": 55, "temp_kf": 0}, "weather": [{"id": 800, "main": "Clear", "description": "clear sky", "icon": "01d"}], "clouds": {"all": 1}, "wind": {"speed": 1.55, "deg": 235}, "sys": {"pod": "d"}, "dt_txt": "2019-11-06 09:00:00"}, {"dt": 1573041600, "main": {"temp": 293.91, "temp_min": 293.91, "temp_max": 293.91, "pressure": 1006, "sea_level": 1006, "grnd_level": 995, "humidity": 44, "temp_kf": 0}, "weather": [{"id": 800, "main": "Clear", "description": "clear sky", "icon": "01d"}], "clouds": {"all": 1}, "wind": {"speed": 1.98, "deg": 253}, "sys": {"pod": "d"}, "dt_txt": "2019-11-06 12:00:00"}, {"dt": 1573052400, "main": {"temp": 291.67, "temp_min": 291.67, "temp_max": 291.67, "pressure": 1005, "sea_level": 1005, "grnd_level": 995, "humidity": 51, "temp_kf": 0}, "weather": [{"id": 800, "main": "Clear", "description": "clear sky", "icon": "01n"}], "clouds": {"all": 4}, "wind": {"speed": 1.66, "deg": 286}, "sys": {"pod": "n"}, "dt_txt": "2019-11-06 15:00:00"}], "city": {"id": 683506, "name": "Bucharest", "coord": {"lat": 44.4323, "lon": 26.1063}, "country": "RO", "timezone": 7200, "sunrise": 1572583925, "sunset": 1572620767}}